Metadata-Version: 2.1
Name: color-log
Version: 1.0.9
Summary: color log terminal and file
Home-page: https://gitee.com/haifengat/general_module
Author: HaiFeng
Author-email: haifengat@vip.qq.com
License: MIT License
Platform: any
Classifier: Programming Language :: Python :: 3
Classifier: Programming Language :: Python :: 3.4
Classifier: Programming Language :: Python :: 3.5
Classifier: Programming Language :: Python :: 3.6
Classifier: Programming Language :: Python :: 3.7
Classifier: License :: OSI Approved :: MIT License
Classifier: Operating System :: OS Independent
Requires-Python: >=3.4.0
